<?xml version="1.0" encoding="UTF-8"?>
<dataSchema name="hdb_adela_H2O" preparer="Heurist user: Adela Sobotkova">
  <!-- ****** -->
  <!--FAIMS Database Schema generated by Heurist Vsn 3.2.0, Tuesday 5th of August 2014 09:45:56 AM-->
  <!-- ****** -->
  <!--Archaeological elements correspond with Heurist record types-->
  <!--Properties correspond with Heurist base field types for this record type-->
  <!--WATER SUPPLY-->
  <ArchaeologicalElement name="Water Supply">
    <description>Water supply monitoring simple form</description>
    <property name="Address of reported problem (optional)" type="blocktext">
      <description>An extended description, use this where text will be limited and does not require any formatting, otherwise use the WYSIWYG text tab to enter formatted text</description>
    </property>
    <property name="Timestamp" type="date">
      <description>timestamp</description>
    </property>
    <property name="Problem Description" type="blocktext">
      <description>Short summary, typically used in annotated listings, information popups and so forth. Aim for 100 - 200 words.</description>
    </property>
    <property name="Problem Frequency" type="enum">
      <description>How often does the problem occur?</description>
      <lookup>
        <term HeuristID="0-5046" StandardCode="">{problem_appears_to_be_permanent}<description/></term>
        <term HeuristID="0-5045" StandardCode="">{sporadically_(no_pattern_apparent_so_far)}<description/></term>
      </lookup>
    </property>
    <property name="Problem Duration" type="enum">
      <description>Describe problem duration with regard to the occurences defined above. E.g. Problem occurs twice a day for 1 hour.</description>
      <lookup>
        <term HeuristID="0-5048" StandardCode="">{1-2_hours}<description/></term>
        <term HeuristID="0-5049" StandardCode="">{2-5_hours}<description/></term>
        <term HeuristID="0-5050" StandardCode="">{more_than_5_hours}<description/></term>
      </lookup>
    </property>
    <property name="Problem Onset" type="enum">
      <description>How would you describe the onset of the problem ? Select from options below</description>
      <lookup>
        <term HeuristID="0-5060" StandardCode="">{Onset_is/was_gradual_and_worsened_with_time}<description/></term>
        <term HeuristID="0-5061" StandardCode="">{Onset_is/was_sudden_at_full_intensity}<description/></term>
      </lookup>
    </property>
    <property name="Problem History" type="enum">
      <description>When did you first notice the problem?</description>
      <lookup>
        <term HeuristID="0-5056" StandardCode="">{Cannot_remember}<description/></term>
        <term HeuristID="0-5054" StandardCode="">{Last_month}<description/></term>
        <term HeuristID="0-5053" StandardCode="">{Last_week}<description/></term>
        <term HeuristID="0-5055" StandardCode="">{Last_year}<description/></term>
        <term HeuristID="0-5052" StandardCode="">{Yesterday}<description/></term>
      </lookup>
    </property>
    <property name="Type of Structure" type="enum">
      <description>Select from a description that best captures the type of structure where problem occurred.</description>
      <lookup>
        <term HeuristID="0-5072" StandardCode="">{Business_Office}<description/></term>
        <term HeuristID="0-5075" StandardCode="">{Other}<description/></term>
        <term HeuristID="0-5069" StandardCode="">{Private_attached_house}<description/></term>
        <term HeuristID="0-5068" StandardCode="">{Private_self-standing_home}<description/></term>
        <term HeuristID="0-5073" StandardCode="">{Public_building}<description/></term>
        <term HeuristID="0-5074" StandardCode="">{Public_space}<description/></term>
        <term HeuristID="0-5063" StandardCode="">{Rental_place/appartment}<description/></term>
        <term HeuristID="0-5064" StandardCode="">{Sublet}<description/></term>
        <term HeuristID="0-5070" StandardCode="">{Vacation_home}<description/></term>
      </lookup>
    </property>
    <property name="Floor where problem noted" type="float">
      <description>Please nominate the highest floor where you noticed the problem</description>
    </property>
  </ArchaeologicalElement>
  <!--ERROR!!!!! This ArchaeologicalEntity does not have identifiers!!! Verify TitleMask in Heurist recordtype!-->
  <!--GPS TRACK-->
  <ArchaeologicalElement name="gps_track">
    <description>A unit is a portion of trench described by this record..</description>
    <property type="integer" name="gps_user" minCardinality="1" maxCardinality="1" isIdentifier="true"/>
    <property type="time" name="gps_timestamp" minCardinality="1" maxCardinality="1" isIdentifier="true"/>
    <property type="text" name="gps_longitude" minCardinality="1" maxCardinality="1" isIdentifier="true"/>
    <property type="text" name="gps_latitude" minCardinality="1" maxCardinality="1" isIdentifier="true"/>
    <property type="float" name="gps_heading" minCardinality="1" maxCardinality="1" isIdentifier="true"/>
    <property type="float" name="gps_accuracy" minCardinality="1" maxCardinality="1" isIdentifier="true"/>
    <property type="text" name="gps_type" minCardinality="1" maxCardinality="1" isIdentifier="true"/>
  </ArchaeologicalElement>
</dataSchema>
